LICENSE
README.md
pyproject.toml
setup.py
e_pandas_stock_quant/__init__.py
e_pandas_stock_quant/core.py
e_pandas_stock_quant.egg-info/PKG-INFO
e_pandas_stock_quant.egg-info/SOURCES.txt
e_pandas_stock_quant.egg-info/dependency_links.txt
e_pandas_stock_quant.egg-info/requires.txt
e_pandas_stock_quant.egg-info/top_level.txt