Metadata-Version: 2.4
Name: e-pandas-stock-quant
Version: 0.1.1
Summary: A pandas-based stock quantitative analysis library
Home-page: https://github.com/rtc2475592453/e-pandas-stock-quant
Author: rtc2475592453
Author-email: 18817223083@163.com
Keywords: pandas,stock,quant,finance,analysis
Classifier: Development Status :: 3 - Alpha
Classifier: Intended Audience :: Financial and Insurance Industry
Classifier: Programming Language :: Python :: 3
Classifier: Programming Language :: Python :: 3.7
Classifier: Programming Language :: Python :: 3.8
Classifier: Programming Language :: Python :: 3.9
Classifier: Programming Language :: Python :: 3.10
Classifier: Programming Language :: Python :: 3.11
Classifier: Programming Language :: Python :: 3.12
Requires-Python: >=3.7
License-File: LICENSE
Requires-Dist: pandas>=1.0.0
Requires-Dist: numpy>=1.0.0
Requires-Dist: scikit-learn>=0.24.0
Requires-Dist: tqdm>=4.0.0
Dynamic: author
Dynamic: author-email
Dynamic: classifier
Dynamic: description
Dynamic: description-content-type
Dynamic: home-page
Dynamic: keywords
Dynamic: license-file
Dynamic: requires-dist
Dynamic: requires-python
Dynamic: summary
